pandas_sets/__init__.py
pandas_sets/sets.py
pandas_sets-0.2.1.dist-info/LICENSE
pandas_sets-0.2.1.dist-info/METADATA
pandas_sets-0.2.1.dist-info/WHEEL
pandas_sets-0.2.1.dist-info/top_level.txt
pandas_sets-0.2.1.dist-info/RECORD
