Metadata-Version: 2.1
Name: pandas-sets
Version: 0.2.1
Summary: Pandas - Sets:  Set-oriented Operations in Pandas
Home-page: https://github.com/Florents-Tselai/pandas-sets
Author: Florents Tselai
Author-email: florents@tselai.com
License: BSD
Platform: UNKNOWN
Requires-Dist: pandas (>=0.24.0)
